sentiment_Lan/__init__.py
sentiment_Lan/sentiment_LanHao.py
sentiment_Lan-0.0.7.dist-info/METADATA
sentiment_Lan-0.0.7.dist-info/WHEEL
sentiment_Lan-0.0.7.dist-info/top_level.txt
sentiment_Lan-0.0.7.dist-info/RECORD
