Metadata-Version: 2.1
Name: sentiment-Lan
Version: 0.0.7
Summary: My first Python package
Home-page: UNKNOWN
Author: Hao Lan
Author-email: lanhao0807@gmail.com
License: UNKNOWN
Keywords: python,first package
Platform: UNKNOWN
Classifier: Development Status :: 3 - Alpha
Classifier: Intended Audience :: Education
Classifier: Programming Language :: Python :: 2
Classifier: Programming Language :: Python :: 3
Classifier: Operating System :: MacOS :: MacOS X
Classifier: Operating System :: Microsoft :: Windows
Requires-Dist: pandas
Requires-Dist: tweepy
Requires-Dist: textblob
